public interface  proguard.classfile.instruction.InstructionConstants extends java.lang.Object
{
    public static final byte ARRAY_T_BOOLEAN;
    public static final byte ARRAY_T_BYTE;
    public static final byte ARRAY_T_CHAR;
    public static final byte ARRAY_T_DOUBLE;
    public static final byte ARRAY_T_FLOAT;
    public static final byte ARRAY_T_INT;
    public static final byte ARRAY_T_LONG;
    public static final byte ARRAY_T_SHORT;
    public static final java.lang.String[] NAMES;
    public static final byte OP_AALOAD;
    public static final byte OP_AASTORE;
    public static final byte OP_ACONST_NULL;
    public static final byte OP_ALOAD;
    public static final byte OP_ALOAD_0;
    public static final byte OP_ALOAD_1;
    public static final byte OP_ALOAD_2;
    public static final byte OP_ALOAD_3;
    public static final byte OP_ANEWARRAY;
    public static final byte OP_ARETURN;
    public static final byte OP_ARRAYLENGTH;
    public static final byte OP_ASTORE;
    public static final byte OP_ASTORE_0;
    public static final byte OP_ASTORE_1;
    public static final byte OP_ASTORE_2;
    public static final byte OP_ASTORE_3;
    public static final byte OP_ATHROW;
    public static final byte OP_BALOAD;
    public static final byte OP_BASTORE;
    public static final byte OP_BIPUSH;
    public static final byte OP_CALOAD;
    public static final byte OP_CASTORE;
    public static final byte OP_CHECKCAST;
    public static final byte OP_D2F;
    public static final byte OP_D2I;
    public static final byte OP_D2L;
    public static final byte OP_DADD;
    public static final byte OP_DALOAD;
    public static final byte OP_DASTORE;
    public static final byte OP_DCMPG;
    public static final byte OP_DCMPL;
    public static final byte OP_DCONST_0;
    public static final byte OP_DCONST_1;
    public static final byte OP_DDIV;
    public static final byte OP_DLOAD;
    public static final byte OP_DLOAD_0;
    public static final byte OP_DLOAD_1;
    public static final byte OP_DLOAD_2;
    public static final byte OP_DLOAD_3;
    public static final byte OP_DMUL;
    public static final byte OP_DNEG;
    public static final byte OP_DREM;
    public static final byte OP_DRETURN;
    public static final byte OP_DSTORE;
    public static final byte OP_DSTORE_0;
    public static final byte OP_DSTORE_1;
    public static final byte OP_DSTORE_2;
    public static final byte OP_DSTORE_3;
    public static final byte OP_DSUB;
    public static final byte OP_DUP;
    public static final byte OP_DUP2;
    public static final byte OP_DUP2_X1;
    public static final byte OP_DUP2_X2;
    public static final byte OP_DUP_X1;
    public static final byte OP_DUP_X2;
    public static final byte OP_F2D;
    public static final byte OP_F2I;
    public static final byte OP_F2L;
    public static final byte OP_FADD;
    public static final byte OP_FALOAD;
    public static final byte OP_FASTORE;
    public static final byte OP_FCMPG;
    public static final byte OP_FCMPL;
    public static final byte OP_FCONST_0;
    public static final byte OP_FCONST_1;
    public static final byte OP_FCONST_2;
    public static final byte OP_FDIV;
    public static final byte OP_FLOAD;
    public static final byte OP_FLOAD_0;
    public static final byte OP_FLOAD_1;
    public static final byte OP_FLOAD_2;
    public static final byte OP_FLOAD_3;
    public static final byte OP_FMUL;
    public static final byte OP_FNEG;
    public static final byte OP_FREM;
    public static final byte OP_FRETURN;
    public static final byte OP_FSTORE;
    public static final byte OP_FSTORE_0;
    public static final byte OP_FSTORE_1;
    public static final byte OP_FSTORE_2;
    public static final byte OP_FSTORE_3;
    public static final byte OP_FSUB;
    public static final byte OP_GETFIELD;
    public static final byte OP_GETSTATIC;
    public static final byte OP_GOTO;
    public static final byte OP_GOTO_W;
    public static final byte OP_I2B;
    public static final byte OP_I2C;
    public static final byte OP_I2D;
    public static final byte OP_I2F;
    public static final byte OP_I2L;
    public static final byte OP_I2S;
    public static final byte OP_IADD;
    public static final byte OP_IALOAD;
    public static final byte OP_IAND;
    public static final byte OP_IASTORE;
    public static final byte OP_ICONST_0;
    public static final byte OP_ICONST_1;
    public static final byte OP_ICONST_2;
    public static final byte OP_ICONST_3;
    public static final byte OP_ICONST_4;
    public static final byte OP_ICONST_5;
    public static final byte OP_ICONST_M1;
    public static final byte OP_IDIV;
    public static final byte OP_IFACMPEQ;
    public static final byte OP_IFACMPNE;
    public static final byte OP_IFEQ;
    public static final byte OP_IFGE;
    public static final byte OP_IFGT;
    public static final byte OP_IFICMPEQ;
    public static final byte OP_IFICMPGE;
    public static final byte OP_IFICMPGT;
    public static final byte OP_IFICMPLE;
    public static final byte OP_IFICMPLT;
    public static final byte OP_IFICMPNE;
    public static final byte OP_IFLE;
    public static final byte OP_IFLT;
    public static final byte OP_IFNE;
    public static final byte OP_IFNONNULL;
    public static final byte OP_IFNULL;
    public static final byte OP_IINC;
    public static final byte OP_ILOAD;
    public static final byte OP_ILOAD_0;
    public static final byte OP_ILOAD_1;
    public static final byte OP_ILOAD_2;
    public static final byte OP_ILOAD_3;
    public static final byte OP_IMUL;
    public static final byte OP_INEG;
    public static final byte OP_INSTANCEOF;
    public static final byte OP_INVOKEINTERFACE;
    public static final byte OP_INVOKESPECIAL;
    public static final byte OP_INVOKESTATIC;
    public static final byte OP_INVOKEVIRTUAL;
    public static final byte OP_IOR;
    public static final byte OP_IREM;
    public static final byte OP_IRETURN;
    public static final byte OP_ISHL;
    public static final byte OP_ISHR;
    public static final byte OP_ISTORE;
    public static final byte OP_ISTORE_0;
    public static final byte OP_ISTORE_1;
    public static final byte OP_ISTORE_2;
    public static final byte OP_ISTORE_3;
    public static final byte OP_ISUB;
    public static final byte OP_IUSHR;
    public static final byte OP_IXOR;
    public static final byte OP_JSR;
    public static final byte OP_JSR_W;
    public static final byte OP_L2D;
    public static final byte OP_L2F;
    public static final byte OP_L2I;
    public static final byte OP_LADD;
    public static final byte OP_LALOAD;
    public static final byte OP_LAND;
    public static final byte OP_LASTORE;
    public static final byte OP_LCMP;
    public static final byte OP_LCONST_0;
    public static final byte OP_LCONST_1;
    public static final byte OP_LDC;
    public static final byte OP_LDC2_W;
    public static final byte OP_LDC_W;
    public static final byte OP_LDIV;
    public static final byte OP_LLOAD;
    public static final byte OP_LLOAD_0;
    public static final byte OP_LLOAD_1;
    public static final byte OP_LLOAD_2;
    public static final byte OP_LLOAD_3;
    public static final byte OP_LMUL;
    public static final byte OP_LNEG;
    public static final byte OP_LOOKUPSWITCH;
    public static final byte OP_LOR;
    public static final byte OP_LREM;
    public static final byte OP_LRETURN;
    public static final byte OP_LSHL;
    public static final byte OP_LSHR;
    public static final byte OP_LSTORE;
    public static final byte OP_LSTORE_0;
    public static final byte OP_LSTORE_1;
    public static final byte OP_LSTORE_2;
    public static final byte OP_LSTORE_3;
    public static final byte OP_LSUB;
    public static final byte OP_LUSHR;
    public static final byte OP_LXOR;
    public static final byte OP_MONITORENTER;
    public static final byte OP_MONITOREXIT;
    public static final byte OP_MULTIANEWARRAY;
    public static final byte OP_NEW;
    public static final byte OP_NEWARRAY;
    public static final byte OP_NOP;
    public static final byte OP_POP;
    public static final byte OP_POP2;
    public static final byte OP_PUTFIELD;
    public static final byte OP_PUTSTATIC;
    public static final byte OP_RET;
    public static final byte OP_RETURN;
    public static final byte OP_SALOAD;
    public static final byte OP_SASTORE;
    public static final byte OP_SIPUSH;
    public static final byte OP_SWAP;
    public static final byte OP_TABLESWITCH;
    public static final byte OP_WIDE;

    static void <clinit>()
    {
        java.lang.String[] $r0;

        <proguard.classfile.instruction.InstructionConstants: byte OP_WIDE> = -60;

        <proguard.classfile.instruction.InstructionConstants: byte OP_TABLESWITCH> = -86;

        <proguard.classfile.instruction.InstructionConstants: byte OP_SWAP> = 95;

        <proguard.classfile.instruction.InstructionConstants: byte OP_SIPUSH> = 17;

        <proguard.classfile.instruction.InstructionConstants: byte OP_SASTORE> = 86;

        <proguard.classfile.instruction.InstructionConstants: byte OP_SALOAD> = 53;

        <proguard.classfile.instruction.InstructionConstants: byte OP_RETURN> = -79;

        <proguard.classfile.instruction.InstructionConstants: byte OP_RET> = -87;

        <proguard.classfile.instruction.InstructionConstants: byte OP_PUTSTATIC> = -77;

        <proguard.classfile.instruction.InstructionConstants: byte OP_PUTFIELD> = -75;

        <proguard.classfile.instruction.InstructionConstants: byte OP_POP2> = 88;

        <proguard.classfile.instruction.InstructionConstants: byte OP_POP> = 87;

        <proguard.classfile.instruction.InstructionConstants: byte OP_NOP> = 0;

        <proguard.classfile.instruction.InstructionConstants: byte OP_NEWARRAY> = -68;

        <proguard.classfile.instruction.InstructionConstants: byte OP_NEW> = -69;

        <proguard.classfile.instruction.InstructionConstants: byte OP_MULTIANEWARRAY> = -59;

        <proguard.classfile.instruction.InstructionConstants: byte OP_MONITOREXIT> = -61;

        <proguard.classfile.instruction.InstructionConstants: byte OP_MONITORENTER> = -62;

        <proguard.classfile.instruction.InstructionConstants: byte OP_LXOR> = -125;

        <proguard.classfile.instruction.InstructionConstants: byte OP_LUSHR> = 125;

        <proguard.classfile.instruction.InstructionConstants: byte OP_LSUB> = 101;

        <proguard.classfile.instruction.InstructionConstants: byte OP_LSTORE_3> = 66;

        <proguard.classfile.instruction.InstructionConstants: byte OP_LSTORE_2> = 65;

        <proguard.classfile.instruction.InstructionConstants: byte OP_LSTORE_1> = 64;

        <proguard.classfile.instruction.InstructionConstants: byte OP_LSTORE_0> = 63;

        <proguard.classfile.instruction.InstructionConstants: byte OP_LSTORE> = 55;

        <proguard.classfile.instruction.InstructionConstants: byte OP_LSHR> = 123;

        <proguard.classfile.instruction.InstructionConstants: byte OP_LSHL> = 121;

        <proguard.classfile.instruction.InstructionConstants: byte OP_LRETURN> = -83;

        <proguard.classfile.instruction.InstructionConstants: byte OP_LREM> = 113;

        <proguard.classfile.instruction.InstructionConstants: byte OP_LOR> = -127;

        <proguard.classfile.instruction.InstructionConstants: byte OP_LOOKUPSWITCH> = -85;

        <proguard.classfile.instruction.InstructionConstants: byte OP_LNEG> = 117;

        <proguard.classfile.instruction.InstructionConstants: byte OP_LMUL> = 105;

        <proguard.classfile.instruction.InstructionConstants: byte OP_LLOAD_3> = 33;

        <proguard.classfile.instruction.InstructionConstants: byte OP_LLOAD_2> = 32;

        <proguard.classfile.instruction.InstructionConstants: byte OP_LLOAD_1> = 31;

        <proguard.classfile.instruction.InstructionConstants: byte OP_LLOAD_0> = 30;

        <proguard.classfile.instruction.InstructionConstants: byte OP_LLOAD> = 22;

        <proguard.classfile.instruction.InstructionConstants: byte OP_LDIV> = 109;

        <proguard.classfile.instruction.InstructionConstants: byte OP_LDC_W> = 19;

        <proguard.classfile.instruction.InstructionConstants: byte OP_LDC2_W> = 20;

        <proguard.classfile.instruction.InstructionConstants: byte OP_LDC> = 18;

        <proguard.classfile.instruction.InstructionConstants: byte OP_LCONST_1> = 10;

        <proguard.classfile.instruction.InstructionConstants: byte OP_LCONST_0> = 9;

        <proguard.classfile.instruction.InstructionConstants: byte OP_LCMP> = -108;

        <proguard.classfile.instruction.InstructionConstants: byte OP_LASTORE> = 80;

        <proguard.classfile.instruction.InstructionConstants: byte OP_LAND> = 127;

        <proguard.classfile.instruction.InstructionConstants: byte OP_LALOAD> = 47;

        <proguard.classfile.instruction.InstructionConstants: byte OP_LADD> = 97;

        <proguard.classfile.instruction.InstructionConstants: byte OP_L2I> = -120;

        <proguard.classfile.instruction.InstructionConstants: byte OP_L2F> = -119;

        <proguard.classfile.instruction.InstructionConstants: byte OP_L2D> = -118;

        <proguard.classfile.instruction.InstructionConstants: byte OP_JSR_W> = -55;

        <proguard.classfile.instruction.InstructionConstants: byte OP_JSR> = -88;

        <proguard.classfile.instruction.InstructionConstants: byte OP_IXOR> = -126;

        <proguard.classfile.instruction.InstructionConstants: byte OP_IUSHR> = 124;

        <proguard.classfile.instruction.InstructionConstants: byte OP_ISUB> = 100;

        <proguard.classfile.instruction.InstructionConstants: byte OP_ISTORE_3> = 62;

        <proguard.classfile.instruction.InstructionConstants: byte OP_ISTORE_2> = 61;

        <proguard.classfile.instruction.InstructionConstants: byte OP_ISTORE_1> = 60;

        <proguard.classfile.instruction.InstructionConstants: byte OP_ISTORE_0> = 59;

        <proguard.classfile.instruction.InstructionConstants: byte OP_ISTORE> = 54;

        <proguard.classfile.instruction.InstructionConstants: byte OP_ISHR> = 122;

        <proguard.classfile.instruction.InstructionConstants: byte OP_ISHL> = 120;

        <proguard.classfile.instruction.InstructionConstants: byte OP_IRETURN> = -84;

        <proguard.classfile.instruction.InstructionConstants: byte OP_IREM> = 112;

        <proguard.classfile.instruction.InstructionConstants: byte OP_IOR> = -128;

        <proguard.classfile.instruction.InstructionConstants: byte OP_INVOKEVIRTUAL> = -74;

        <proguard.classfile.instruction.InstructionConstants: byte OP_INVOKESTATIC> = -72;

        <proguard.classfile.instruction.InstructionConstants: byte OP_INVOKESPECIAL> = -73;

        <proguard.classfile.instruction.InstructionConstants: byte OP_INVOKEINTERFACE> = -71;

        <proguard.classfile.instruction.InstructionConstants: byte OP_INSTANCEOF> = -63;

        <proguard.classfile.instruction.InstructionConstants: byte OP_INEG> = 116;

        <proguard.classfile.instruction.InstructionConstants: byte OP_IMUL> = 104;

        <proguard.classfile.instruction.InstructionConstants: byte OP_ILOAD_3> = 29;

        <proguard.classfile.instruction.InstructionConstants: byte OP_ILOAD_2> = 28;

        <proguard.classfile.instruction.InstructionConstants: byte OP_ILOAD_1> = 27;

        <proguard.classfile.instruction.InstructionConstants: byte OP_ILOAD_0> = 26;

        <proguard.classfile.instruction.InstructionConstants: byte OP_ILOAD> = 21;

        <proguard.classfile.instruction.InstructionConstants: byte OP_IINC> = -124;

        <proguard.classfile.instruction.InstructionConstants: byte OP_IFNULL> = -58;

        <proguard.classfile.instruction.InstructionConstants: byte OP_IFNONNULL> = -57;

        <proguard.classfile.instruction.InstructionConstants: byte OP_IFNE> = -102;

        <proguard.classfile.instruction.InstructionConstants: byte OP_IFLT> = -101;

        <proguard.classfile.instruction.InstructionConstants: byte OP_IFLE> = -98;

        <proguard.classfile.instruction.InstructionConstants: byte OP_IFICMPNE> = -96;

        <proguard.classfile.instruction.InstructionConstants: byte OP_IFICMPLT> = -95;

        <proguard.classfile.instruction.InstructionConstants: byte OP_IFICMPLE> = -92;

        <proguard.classfile.instruction.InstructionConstants: byte OP_IFICMPGT> = -93;

        <proguard.classfile.instruction.InstructionConstants: byte OP_IFICMPGE> = -94;

        <proguard.classfile.instruction.InstructionConstants: byte OP_IFICMPEQ> = -97;

        <proguard.classfile.instruction.InstructionConstants: byte OP_IFGT> = -99;

        <proguard.classfile.instruction.InstructionConstants: byte OP_IFGE> = -100;

        <proguard.classfile.instruction.InstructionConstants: byte OP_IFEQ> = -103;

        <proguard.classfile.instruction.InstructionConstants: byte OP_IFACMPNE> = -90;

        <proguard.classfile.instruction.InstructionConstants: byte OP_IFACMPEQ> = -91;

        <proguard.classfile.instruction.InstructionConstants: byte OP_IDIV> = 108;

        <proguard.classfile.instruction.InstructionConstants: byte OP_ICONST_M1> = 2;

        <proguard.classfile.instruction.InstructionConstants: byte OP_ICONST_5> = 8;

        <proguard.classfile.instruction.InstructionConstants: byte OP_ICONST_4> = 7;

        <proguard.classfile.instruction.InstructionConstants: byte OP_ICONST_3> = 6;

        <proguard.classfile.instruction.InstructionConstants: byte OP_ICONST_2> = 5;

        <proguard.classfile.instruction.InstructionConstants: byte OP_ICONST_1> = 4;

        <proguard.classfile.instruction.InstructionConstants: byte OP_ICONST_0> = 3;

        <proguard.classfile.instruction.InstructionConstants: byte OP_IASTORE> = 79;

        <proguard.classfile.instruction.InstructionConstants: byte OP_IAND> = 126;

        <proguard.classfile.instruction.InstructionConstants: byte OP_IALOAD> = 46;

        <proguard.classfile.instruction.InstructionConstants: byte OP_IADD> = 96;

        <proguard.classfile.instruction.InstructionConstants: byte OP_I2S> = -109;

        <proguard.classfile.instruction.InstructionConstants: byte OP_I2L> = -123;

        <proguard.classfile.instruction.InstructionConstants: byte OP_I2F> = -122;

        <proguard.classfile.instruction.InstructionConstants: byte OP_I2D> = -121;

        <proguard.classfile.instruction.InstructionConstants: byte OP_I2C> = -110;

        <proguard.classfile.instruction.InstructionConstants: byte OP_I2B> = -111;

        <proguard.classfile.instruction.InstructionConstants: byte OP_GOTO_W> = -56;

        <proguard.classfile.instruction.InstructionConstants: byte OP_GOTO> = -89;

        <proguard.classfile.instruction.InstructionConstants: byte OP_GETSTATIC> = -78;

        <proguard.classfile.instruction.InstructionConstants: byte OP_GETFIELD> = -76;

        <proguard.classfile.instruction.InstructionConstants: byte OP_FSUB> = 102;

        <proguard.classfile.instruction.InstructionConstants: byte OP_FSTORE_3> = 70;

        <proguard.classfile.instruction.InstructionConstants: byte OP_FSTORE_2> = 69;

        <proguard.classfile.instruction.InstructionConstants: byte OP_FSTORE_1> = 68;

        <proguard.classfile.instruction.InstructionConstants: byte OP_FSTORE_0> = 67;

        <proguard.classfile.instruction.InstructionConstants: byte OP_FSTORE> = 56;

        <proguard.classfile.instruction.InstructionConstants: byte OP_FRETURN> = -82;

        <proguard.classfile.instruction.InstructionConstants: byte OP_FREM> = 114;

        <proguard.classfile.instruction.InstructionConstants: byte OP_FNEG> = 118;

        <proguard.classfile.instruction.InstructionConstants: byte OP_FMUL> = 106;

        <proguard.classfile.instruction.InstructionConstants: byte OP_FLOAD_3> = 37;

        <proguard.classfile.instruction.InstructionConstants: byte OP_FLOAD_2> = 36;

        <proguard.classfile.instruction.InstructionConstants: byte OP_FLOAD_1> = 35;

        <proguard.classfile.instruction.InstructionConstants: byte OP_FLOAD_0> = 34;

        <proguard.classfile.instruction.InstructionConstants: byte OP_FLOAD> = 23;

        <proguard.classfile.instruction.InstructionConstants: byte OP_FDIV> = 110;

        <proguard.classfile.instruction.InstructionConstants: byte OP_FCONST_2> = 13;

        <proguard.classfile.instruction.InstructionConstants: byte OP_FCONST_1> = 12;

        <proguard.classfile.instruction.InstructionConstants: byte OP_FCONST_0> = 11;

        <proguard.classfile.instruction.InstructionConstants: byte OP_FCMPL> = -107;

        <proguard.classfile.instruction.InstructionConstants: byte OP_FCMPG> = -106;

        <proguard.classfile.instruction.InstructionConstants: byte OP_FASTORE> = 81;

        <proguard.classfile.instruction.InstructionConstants: byte OP_FALOAD> = 48;

        <proguard.classfile.instruction.InstructionConstants: byte OP_FADD> = 98;

        <proguard.classfile.instruction.InstructionConstants: byte OP_F2L> = -116;

        <proguard.classfile.instruction.InstructionConstants: byte OP_F2I> = -117;

        <proguard.classfile.instruction.InstructionConstants: byte OP_F2D> = -115;

        <proguard.classfile.instruction.InstructionConstants: byte OP_DUP_X2> = 91;

        <proguard.classfile.instruction.InstructionConstants: byte OP_DUP_X1> = 90;

        <proguard.classfile.instruction.InstructionConstants: byte OP_DUP2_X2> = 94;

        <proguard.classfile.instruction.InstructionConstants: byte OP_DUP2_X1> = 93;

        <proguard.classfile.instruction.InstructionConstants: byte OP_DUP2> = 92;

        <proguard.classfile.instruction.InstructionConstants: byte OP_DUP> = 89;

        <proguard.classfile.instruction.InstructionConstants: byte OP_DSUB> = 103;

        <proguard.classfile.instruction.InstructionConstants: byte OP_DSTORE_3> = 74;

        <proguard.classfile.instruction.InstructionConstants: byte OP_DSTORE_2> = 73;

        <proguard.classfile.instruction.InstructionConstants: byte OP_DSTORE_1> = 72;

        <proguard.classfile.instruction.InstructionConstants: byte OP_DSTORE_0> = 71;

        <proguard.classfile.instruction.InstructionConstants: byte OP_DSTORE> = 57;

        <proguard.classfile.instruction.InstructionConstants: byte OP_DRETURN> = -81;

        <proguard.classfile.instruction.InstructionConstants: byte OP_DREM> = 115;

        <proguard.classfile.instruction.InstructionConstants: byte OP_DNEG> = 119;

        <proguard.classfile.instruction.InstructionConstants: byte OP_DMUL> = 107;

        <proguard.classfile.instruction.InstructionConstants: byte OP_DLOAD_3> = 41;

        <proguard.classfile.instruction.InstructionConstants: byte OP_DLOAD_2> = 40;

        <proguard.classfile.instruction.InstructionConstants: byte OP_DLOAD_1> = 39;

        <proguard.classfile.instruction.InstructionConstants: byte OP_DLOAD_0> = 38;

        <proguard.classfile.instruction.InstructionConstants: byte OP_DLOAD> = 24;

        <proguard.classfile.instruction.InstructionConstants: byte OP_DDIV> = 111;

        <proguard.classfile.instruction.InstructionConstants: byte OP_DCONST_1> = 15;

        <proguard.classfile.instruction.InstructionConstants: byte OP_DCONST_0> = 14;

        <proguard.classfile.instruction.InstructionConstants: byte OP_DCMPL> = -105;

        <proguard.classfile.instruction.InstructionConstants: byte OP_DCMPG> = -104;

        <proguard.classfile.instruction.InstructionConstants: byte OP_DASTORE> = 82;

        <proguard.classfile.instruction.InstructionConstants: byte OP_DALOAD> = 49;

        <proguard.classfile.instruction.InstructionConstants: byte OP_DADD> = 99;

        <proguard.classfile.instruction.InstructionConstants: byte OP_D2L> = -113;

        <proguard.classfile.instruction.InstructionConstants: byte OP_D2I> = -114;

        <proguard.classfile.instruction.InstructionConstants: byte OP_D2F> = -112;

        <proguard.classfile.instruction.InstructionConstants: byte OP_CHECKCAST> = -64;

        <proguard.classfile.instruction.InstructionConstants: byte OP_CASTORE> = 85;

        <proguard.classfile.instruction.InstructionConstants: byte OP_CALOAD> = 52;

        <proguard.classfile.instruction.InstructionConstants: byte OP_BIPUSH> = 16;

        <proguard.classfile.instruction.InstructionConstants: byte OP_BASTORE> = 84;

        <proguard.classfile.instruction.InstructionConstants: byte OP_BALOAD> = 51;

        <proguard.classfile.instruction.InstructionConstants: byte OP_ATHROW> = -65;

        <proguard.classfile.instruction.InstructionConstants: byte OP_ASTORE_3> = 78;

        <proguard.classfile.instruction.InstructionConstants: byte OP_ASTORE_2> = 77;

        <proguard.classfile.instruction.InstructionConstants: byte OP_ASTORE_1> = 76;

        <proguard.classfile.instruction.InstructionConstants: byte OP_ASTORE_0> = 75;

        <proguard.classfile.instruction.InstructionConstants: byte OP_ASTORE> = 58;

        <proguard.classfile.instruction.InstructionConstants: byte OP_ARRAYLENGTH> = -66;

        <proguard.classfile.instruction.InstructionConstants: byte OP_ARETURN> = -80;

        <proguard.classfile.instruction.InstructionConstants: byte OP_ANEWARRAY> = -67;

        <proguard.classfile.instruction.InstructionConstants: byte OP_ALOAD_3> = 45;

        <proguard.classfile.instruction.InstructionConstants: byte OP_ALOAD_2> = 44;

        <proguard.classfile.instruction.InstructionConstants: byte OP_ALOAD_1> = 43;

        <proguard.classfile.instruction.InstructionConstants: byte OP_ALOAD_0> = 42;

        <proguard.classfile.instruction.InstructionConstants: byte OP_ALOAD> = 25;

        <proguard.classfile.instruction.InstructionConstants: byte OP_ACONST_NULL> = 1;

        <proguard.classfile.instruction.InstructionConstants: byte OP_AASTORE> = 83;

        <proguard.classfile.instruction.InstructionConstants: byte OP_AALOAD> = 50;

        <proguard.classfile.instruction.InstructionConstants: byte ARRAY_T_SHORT> = 9;

        <proguard.classfile.instruction.InstructionConstants: byte ARRAY_T_LONG> = 11;

        <proguard.classfile.instruction.InstructionConstants: byte ARRAY_T_INT> = 10;

        <proguard.classfile.instruction.InstructionConstants: byte ARRAY_T_FLOAT> = 6;

        <proguard.classfile.instruction.InstructionConstants: byte ARRAY_T_DOUBLE> = 7;

        <proguard.classfile.instruction.InstructionConstants: byte ARRAY_T_CHAR> = 5;

        <proguard.classfile.instruction.InstructionConstants: byte ARRAY_T_BYTE> = 8;

        <proguard.classfile.instruction.InstructionConstants: byte ARRAY_T_BOOLEAN> = 4;

        $r0 = newarray (java.lang.String)[202];

        $r0[0] = "nop";

        $r0[1] = "aconst_null";

        $r0[2] = "iconst_m1";

        $r0[3] = "iconst_0";

        $r0[4] = "iconst_1";

        $r0[5] = "iconst_2";

        $r0[6] = "iconst_3";

        $r0[7] = "iconst_4";

        $r0[8] = "iconst_5";

        $r0[9] = "lconst_0";

        $r0[10] = "lconst_1";

        $r0[11] = "fconst_0";

        $r0[12] = "fconst_1";

        $r0[13] = "fconst_2";

        $r0[14] = "dconst_0";

        $r0[15] = "dconst_1";

        $r0[16] = "bipush";

        $r0[17] = "sipush";

        $r0[18] = "ldc";

        $r0[19] = "ldc_w";

        $r0[20] = "ldc2_w";

        $r0[21] = "iload";

        $r0[22] = "lload";

        $r0[23] = "fload";

        $r0[24] = "dload";

        $r0[25] = "aload";

        $r0[26] = "iload_0";

        $r0[27] = "iload_1";

        $r0[28] = "iload_2";

        $r0[29] = "iload_3";

        $r0[30] = "lload_0";

        $r0[31] = "lload_1";

        $r0[32] = "lload_2";

        $r0[33] = "lload_3";

        $r0[34] = "fload_0";

        $r0[35] = "fload_1";

        $r0[36] = "fload_2";

        $r0[37] = "fload_3";

        $r0[38] = "dload_0";

        $r0[39] = "dload_1";

        $r0[40] = "dload_2";

        $r0[41] = "dload_3";

        $r0[42] = "aload_0";

        $r0[43] = "aload_1";

        $r0[44] = "aload_2";

        $r0[45] = "aload_3";

        $r0[46] = "iaload";

        $r0[47] = "laload";

        $r0[48] = "faload";

        $r0[49] = "daload";

        $r0[50] = "aaload";

        $r0[51] = "baload";

        $r0[52] = "caload";

        $r0[53] = "saload";

        $r0[54] = "istore";

        $r0[55] = "lstore";

        $r0[56] = "fstore";

        $r0[57] = "dstore";

        $r0[58] = "astore";

        $r0[59] = "istore_0";

        $r0[60] = "istore_1";

        $r0[61] = "istore_2";

        $r0[62] = "istore_3";

        $r0[63] = "lstore_0";

        $r0[64] = "lstore_1";

        $r0[65] = "lstore_2";

        $r0[66] = "lstore_3";

        $r0[67] = "fstore_0";

        $r0[68] = "fstore_1";

        $r0[69] = "fstore_2";

        $r0[70] = "fstore_3";

        $r0[71] = "dstore_0";

        $r0[72] = "dstore_1";

        $r0[73] = "dstore_2";

        $r0[74] = "dstore_3";

        $r0[75] = "astore_0";

        $r0[76] = "astore_1";

        $r0[77] = "astore_2";

        $r0[78] = "astore_3";

        $r0[79] = "iastore";

        $r0[80] = "lastore";

        $r0[81] = "fastore";

        $r0[82] = "dastore";

        $r0[83] = "aastore";

        $r0[84] = "bastore";

        $r0[85] = "castore";

        $r0[86] = "sastore";

        $r0[87] = "pop";

        $r0[88] = "pop2";

        $r0[89] = "dup";

        $r0[90] = "dup_x1";

        $r0[91] = "dup_x2";

        $r0[92] = "dup2";

        $r0[93] = "dup2_x1";

        $r0[94] = "dup2_x2";

        $r0[95] = "swap";

        $r0[96] = "iadd";

        $r0[97] = "ladd";

        $r0[98] = "fadd";

        $r0[99] = "dadd";

        $r0[100] = "isub";

        $r0[101] = "lsub";

        $r0[102] = "fsub";

        $r0[103] = "dsub";

        $r0[104] = "imul";

        $r0[105] = "lmul";

        $r0[106] = "fmul";

        $r0[107] = "dmul";

        $r0[108] = "idiv";

        $r0[109] = "ldiv";

        $r0[110] = "fdiv";

        $r0[111] = "ddiv";

        $r0[112] = "irem";

        $r0[113] = "lrem";

        $r0[114] = "frem";

        $r0[115] = "drem";

        $r0[116] = "ineg";

        $r0[117] = "lneg";

        $r0[118] = "fneg";

        $r0[119] = "dneg";

        $r0[120] = "ishl";

        $r0[121] = "lshl";

        $r0[122] = "ishr";

        $r0[123] = "lshr";

        $r0[124] = "iushr";

        $r0[125] = "lushr";

        $r0[126] = "iand";

        $r0[127] = "land";

        $r0[128] = "ior";

        $r0[129] = "lor";

        $r0[130] = "ixor";

        $r0[131] = "lxor";

        $r0[132] = "iinc";

        $r0[133] = "i2l";

        $r0[134] = "i2f";

        $r0[135] = "i2d";

        $r0[136] = "l2i";

        $r0[137] = "l2f";

        $r0[138] = "l2d";

        $r0[139] = "f2i";

        $r0[140] = "f2l";

        $r0[141] = "f2d";

        $r0[142] = "d2i";

        $r0[143] = "d2l";

        $r0[144] = "d2f";

        $r0[145] = "i2b";

        $r0[146] = "i2c";

        $r0[147] = "i2s";

        $r0[148] = "lcmp";

        $r0[149] = "fcmpl";

        $r0[150] = "fcmpg";

        $r0[151] = "dcmpl";

        $r0[152] = "dcmpg";

        $r0[153] = "ifeq";

        $r0[154] = "ifne";

        $r0[155] = "iflt";

        $r0[156] = "ifge";

        $r0[157] = "ifgt";

        $r0[158] = "ifle";

        $r0[159] = "ificmpeq";

        $r0[160] = "ificmpne";

        $r0[161] = "ificmplt";

        $r0[162] = "ificmpge";

        $r0[163] = "ificmpgt";

        $r0[164] = "ificmple";

        $r0[165] = "ifacmpeq";

        $r0[166] = "ifacmpne";

        $r0[167] = "goto";

        $r0[168] = "jsr";

        $r0[169] = "ret";

        $r0[170] = "tableswitch";

        $r0[171] = "lookupswitch";

        $r0[172] = "ireturn";

        $r0[173] = "lreturn";

        $r0[174] = "freturn";

        $r0[175] = "dreturn";

        $r0[176] = "areturn";

        $r0[177] = "return";

        $r0[178] = "getstatic";

        $r0[179] = "putstatic";

        $r0[180] = "getfield";

        $r0[181] = "putfield";

        $r0[182] = "invokevirtual";

        $r0[183] = "invokespecial";

        $r0[184] = "invokestatic";

        $r0[185] = "invokeinterface";

        $r0[186] = "unused";

        $r0[187] = "new";

        $r0[188] = "newarray";

        $r0[189] = "anewarray";

        $r0[190] = "arraylength";

        $r0[191] = "athrow";

        $r0[192] = "checkcast";

        $r0[193] = "instanceof";

        $r0[194] = "monitorenter";

        $r0[195] = "monitorexit";

        $r0[196] = "wide";

        $r0[197] = "multianewarray";

        $r0[198] = "ifnull";

        $r0[199] = "ifnonnull";

        $r0[200] = "goto_w";

        $r0[201] = "jsr_w";

        <proguard.classfile.instruction.InstructionConstants: java.lang.String[] NAMES> = $r0;

        return;
    }
}
